idox/__init__.py
idox/__main__.py
idox/case_insensitive_dict.py
idox/exceptions.py
idox/idox.py
idox/sequences.py
idox/structs.py
idox-1.4.0.dist-info/METADATA
idox-1.4.0.dist-info/WHEEL
idox-1.4.0.dist-info/licenses/LICENSE
idox-1.4.0.dist-info/RECORD
