Metadata-Version: 2.4
Name: idox
Version: 1.4.0
Summary: IDOR file downloader using HTTP request files.
Project-URL: Issue tracker, https://github.com/Skelmis/idox/issues
Project-URL: Homepage, https://github.com/Skelmis/idox
Author-email: skelmis <skelmis.craft@gmail.com>
License-Expression: MIT
License-File: LICENSE
Classifier: License :: OSI Approved :: MIT License
Classifier: Operating System :: OS Independent
Classifier: Programming Language :: Python :: 3
Requires-Python: >=3.10
Requires-Dist: black>=25.1.0
Requires-Dist: httpx>=0.27.2
Requires-Dist: orjson>=3.10.10
Requires-Dist: skelmis-commons>=1.4.0
Requires-Dist: typer>=0.12.5
